cmdi/__init__.py
cmdi/decorator.py
cmdi/lib.py
cmdi/redirector.py
cmdi-3.1.2.dist-info/METADATA
cmdi-3.1.2.dist-info/WHEEL
cmdi-3.1.2.dist-info/licenses/LICENSE
cmdi-3.1.2.dist-info/RECORD
