Metadata-Version: 2.4
Name: cmdi
Version: 3.1.2
Summary: A command interface
License: Apache-2.0
License-File: LICENSE
Keywords: command,interface,wrapper,handler,capture,stdout,stderr
Author: feluxe
Author-email: felix@meyerwolters.de
Maintainer: feluxe
Maintainer-email: felix@meyerwolters.de
Requires-Python: >=3.9,<4.0
Classifier: License :: OSI Approved :: Apache Software License
Classifier: Programming Language :: Python :: 3
Classifier: Programming Language :: Python :: 3.9
Classifier: Programming Language :: Python :: 3.10
Classifier: Programming Language :: Python :: 3.11
Classifier: Programming Language :: Python :: 3.12
Classifier: Programming Language :: Python :: 3.13
Classifier: Programming Language :: Python :: 3.14
Requires-Dist: typing-extensions (>=4.15.0,<5.0.0)
Project-URL: Repository, https://github.com/feluxe/cmdi
